tests/__init__.py
tests/test_iso.py
isoai-0.0.3.dist-info/LICENSE
isoai-0.0.3.dist-info/METADATA
isoai-0.0.3.dist-info/WHEEL
isoai-0.0.3.dist-info/top_level.txt
isoai-0.0.3.dist-info/RECORD
