Metadata-Version: 2.1
Name: isoai
Version: 0.0.3
Summary: Compress, Trace and Deploy Your Models with Iso!
Home-page: https://github.com/iso-ai/isosdk
Author: Jazmia Henry
Author-email: isojaz@isoai.co
License: UNKNOWN
Platform: UNKNOWN
Classifier: Development Status :: 2 - Pre-Alpha
Classifier: Programming Language :: Python :: 3
Classifier: License :: OSI Approved :: Apache Software License
Classifier: Operating System :: OS Independent
Requires-Python: >=3.6
License-File: LICENSE
Requires-Dist: torch (>=1.7.1)
